helloworld.py
helloworld_dwitch-0.0.1.dist-info/LICENSE.txt
helloworld_dwitch-0.0.1.dist-info/METADATA
helloworld_dwitch-0.0.1.dist-info/WHEEL
helloworld_dwitch-0.0.1.dist-info/top_level.txt
helloworld_dwitch-0.0.1.dist-info/RECORD
